{
 "custom_fields": [
  {
   "_assign": null, 
   "_comments": null, 
   "_liked_by": null, 
   "_user_tags": null, 
   "allow_on_submit": 1, 
   "bold": 0, 
   "collapsible": 0, 
   "collapsible_depends_on": null, 
   "columns": 0, 
   "creation": "2020-01-02 13:54:19.956276", 
   "default": null, 
   "depends_on": null, 
   "description": null, 
   "docstatus": 0, 
   "dt": "Timesheet", 
   "fetch_from": null, 
   "fetch_if_empty": 0, 
   "fieldname": "workflow_state", 
   "fieldtype": "Link", 
   "hidden": 1, 
   "idx": 0, 
   "ignore_user_permissions": 0, 
   "ignore_xss_filter": 0, 
   "in_filter": 0, 
   "in_filter_dash": 0, 
   "in_global_search": 0, 
   "in_list_view": 0, 
   "in_standard_filter": 0, 
   "insert_after": null, 
   "label": "Workflow State", 
   "modified": "2020-01-02 13:54:19.956276", 
   "modified_by": "blefebvre@aptitudetech.net", 
   "name": "Timesheet-workflow_state", 
   "no_copy": 1, 
   "options": "Workflow State", 
   "owner": "Administrator", 
   "parent": null, 
   "parentfield": null, 
   "parenttype": null, 
   "permlevel": 0, 
   "precision": "", 
   "print_hide": 0, 
   "print_hide_if_no_value": 0, 
   "print_width": null, 
   "read_only": 0, 
   "report_hide": 0, 
   "reqd": 0, 
   "search_index": 0, 
   "translatable": 0, 
   "unique": 0, 
   "width": null
  }
 ], 
 "custom_perms": [], 
 "doctype": "Timesheet", 
 "property_setters": [
  {
   "_assign": null, 
   "_comments": null, 
   "_liked_by": null, 
   "_user_tags": null, 
   "creation": "2016-08-02 09:25:08.446976", 
   "default_value": null, 
   "doc_type": "Timesheet", 
   "docstatus": 0, 
   "doctype_or_field": "DocField", 
   "field_name": "naming_series", 
   "idx": 0, 
   "modified": "2020-01-03 12:38:01.865820", 
   "modified_by": "Administrator", 
   "name": "Timesheet-naming_series-options", 
   "owner": "Administrator", 
   "parent": null, 
   "parentfield": null, 
   "parenttype": null, 
   "property": "options", 
   "property_type": "Text", 
   "value": "TS-.YY.-.MM.-.####"
  }, 
  {
   "_assign": null, 
   "_comments": null, 
   "_liked_by": null, 
   "_user_tags": null, 
   "creation": "2016-08-02 09:25:08.466199", 
   "default_value": null, 
   "doc_type": "Timesheet", 
   "docstatus": 0, 
   "doctype_or_field": "DocField", 
   "field_name": "naming_series", 
   "idx": 0, 
   "modified": "2020-01-03 12:38:01.801425", 
   "modified_by": "Administrator", 
   "name": "Timesheet-naming_series-default", 
   "owner": "Administrator", 
   "parent": null, 
   "parentfield": null, 
   "parenttype": null, 
   "property": "default", 
   "property_type": "Text", 
   "value": "TS-.YY.-.MM.-.####"
  }, 
  {
   "_assign": null, 
   "_comments": null, 
   "_liked_by": null, 
   "_user_tags": null, 
   "creation": "2020-01-02 13:24:26.697898", 
   "default_value": null, 
   "doc_type": "Timesheet", 
   "docstatus": 0, 
   "doctype_or_field": "DocField", 
   "field_name": "note", 
   "idx": 0, 
   "modified": "2020-01-02 13:24:26.697898", 
   "modified_by": "blefebvre@aptitudetech.net", 
   "name": "Timesheet-note-hidden", 
   "owner": "blefebvre@aptitudetech.net", 
   "parent": null, 
   "parentfield": null, 
   "parenttype": null, 
   "property": "hidden", 
   "property_type": "Check", 
   "value": "1"
  }, 
  {
   "_assign": null, 
   "_comments": null, 
   "_liked_by": null, 
   "_user_tags": null, 
   "creation": "2020-01-02 13:24:26.668995", 
   "default_value": null, 
   "doc_type": "Timesheet", 
   "docstatus": 0, 
   "doctype_or_field": "DocType", 
   "field_name": null, 
   "idx": 0, 
   "modified": "2020-01-02 13:24:26.668995", 
   "modified_by": "blefebvre@aptitudetech.net", 
   "name": "Timesheet-read_only_onload", 
   "owner": "blefebvre@aptitudetech.net", 
   "parent": null, 
   "parentfield": null, 
   "parenttype": null, 
   "property": "read_only_onload", 
   "property_type": "Check", 
   "value": null
  }, 
  {
   "_assign": null, 
   "_comments": null, 
   "_liked_by": null, 
   "_user_tags": null, 
   "creation": "2018-05-23 16:00:30.205223", 
   "default_value": null, 
   "doc_type": "Timesheet", 
   "docstatus": 0, 
   "doctype_or_field": "DocField", 
   "field_name": "employee_name", 
   "idx": 0, 
   "modified": "2018-05-23 16:00:30.205223", 
   "modified_by": "braultca@videotron.ca", 
   "name": "Timesheet-employee_name-width", 
   "owner": "braultca@videotron.ca", 
   "parent": null, 
   "parentfield": null, 
   "parenttype": null, 
   "property": "width", 
   "property_type": null, 
   "value": "104"
  }, 
  {
   "_assign": null, 
   "_comments": null, 
   "_liked_by": null, 
   "_user_tags": null, 
   "creation": "2018-05-23 16:00:26.583280", 
   "default_value": null, 
   "doc_type": "Timesheet", 
   "docstatus": 0, 
   "doctype_or_field": "DocField", 
   "field_name": "employee", 
   "idx": 0, 
   "modified": "2018-05-23 16:00:26.583280", 
   "modified_by": "braultca@videotron.ca", 
   "name": "Timesheet-employee-width", 
   "owner": "braultca@videotron.ca", 
   "parent": null, 
   "parentfield": null, 
   "parenttype": null, 
   "property": "width", 
   "property_type": null, 
   "value": "161"
  }, 
  {
   "_assign": null, 
   "_comments": null, 
   "_liked_by": null, 
   "_user_tags": null, 
   "creation": "2018-01-16 10:52:00.327127", 
   "default_value": null, 
   "doc_type": "Timesheet", 
   "docstatus": 0, 
   "doctype_or_field": "DocField", 
   "field_name": "status", 
   "idx": 0, 
   "modified": "2018-01-16 10:52:00.327127", 
   "modified_by": "blefebvre@aptitudetech.net", 
   "name": "Timesheet-status-width", 
   "owner": "blefebvre@aptitudetech.net", 
   "parent": null, 
   "parentfield": null, 
   "parenttype": null, 
   "property": "width", 
   "property_type": null, 
   "value": "66"
  }, 
  {
   "_assign": null, 
   "_comments": null, 
   "_liked_by": null, 
   "_user_tags": null, 
   "creation": "2017-08-31 07:43:46.815293", 
   "default_value": null, 
   "doc_type": "Timesheet", 
   "docstatus": 0, 
   "doctype_or_field": "DocField", 
   "field_name": "total_hours", 
   "idx": 0, 
   "modified": "2017-08-31 07:43:46.815293", 
   "modified_by": "blefebvre@aptitudetech.net", 
   "name": "Timesheet-total_hours-width", 
   "owner": "blefebvre@aptitudetech.net", 
   "parent": null, 
   "parentfield": null, 
   "parenttype": null, 
   "property": "width", 
   "property_type": null, 
   "value": "134"
  }, 
  {
   "_assign": null, 
   "_comments": null, 
   "_liked_by": null, 
   "_user_tags": null, 
   "creation": "2017-03-23 23:41:50.897096", 
   "default_value": null, 
   "doc_type": "Timesheet", 
   "docstatus": 0, 
   "doctype_or_field": "DocField", 
   "field_name": "total_billable_amount", 
   "idx": 0, 
   "modified": "2017-03-23 23:41:50.897096", 
   "modified_by": "blefebvre@aptitudetech.net", 
   "name": "Timesheet-total_billable_amount-width", 
   "owner": "blefebvre@aptitudetech.net", 
   "parent": null, 
   "parentfield": null, 
   "parenttype": null, 
   "property": "width", 
   "property_type": null, 
   "value": "148"
  }, 
  {
   "_assign": null, 
   "_comments": null, 
   "_liked_by": null, 
   "_user_tags": null, 
   "creation": "2016-10-05 21:25:53.444708", 
   "default_value": null, 
   "doc_type": "Timesheet", 
   "docstatus": 0, 
   "doctype_or_field": "DocField", 
   "field_name": "time_logs", 
   "idx": 0, 
   "modified": "2016-10-05 21:25:53.444708", 
   "modified_by": "blefebvre@aptitudetech.net", 
   "name": "Timesheet-time_logs-permlevel", 
   "owner": "blefebvre@aptitudetech.net", 
   "parent": null, 
   "parentfield": null, 
   "parenttype": null, 
   "property": "permlevel", 
   "property_type": "Int", 
   "value": null
  }, 
  {
   "_assign": null, 
   "_comments": null, 
   "_liked_by": null, 
   "_user_tags": null, 
   "creation": "2016-10-03 21:16:11.226990", 
   "default_value": null, 
   "doc_type": "Timesheet", 
   "docstatus": 0, 
   "doctype_or_field": "DocField", 
   "field_name": "total_hours", 
   "idx": 0, 
   "modified": "2016-10-03 21:16:11.226990", 
   "modified_by": "blefebvre@aptitudetech.net", 
   "name": "Timesheet-total_hours-in_list_view", 
   "owner": "blefebvre@aptitudetech.net", 
   "parent": null, 
   "parentfield": null, 
   "parenttype": null, 
   "property": "in_list_view", 
   "property_type": "Check", 
   "value": "0"
  }, 
  {
   "_assign": null, 
   "_comments": null, 
   "_liked_by": null, 
   "_user_tags": null, 
   "creation": "2016-10-03 21:16:11.221630", 
   "default_value": null, 
   "doc_type": "Timesheet", 
   "docstatus": 0, 
   "doctype_or_field": "DocField", 
   "field_name": "employee_name", 
   "idx": 0, 
   "modified": "2016-10-03 21:16:11.221630", 
   "modified_by": "blefebvre@aptitudetech.net", 
   "name": "Timesheet-employee_name-in_list_view", 
   "owner": "blefebvre@aptitudetech.net", 
   "parent": null, 
   "parentfield": null, 
   "parenttype": null, 
   "property": "in_list_view", 
   "property_type": "Check", 
   "value": "1"
  }, 
  {
   "_assign": null, 
   "_comments": null, 
   "_liked_by": null, 
   "_user_tags": null, 
   "creation": "2016-09-22 23:17:23.329924", 
   "default_value": null, 
   "doc_type": "Timesheet", 
   "docstatus": 0, 
   "doctype_or_field": "DocField", 
   "field_name": "total_costing_amount", 
   "idx": 0, 
   "modified": "2016-09-22 23:17:23.329924", 
   "modified_by": "blefebvre@aptitudetech.net", 
   "name": "Timesheet-total_costing_amount-permlevel", 
   "owner": "blefebvre@aptitudetech.net", 
   "parent": null, 
   "parentfield": null, 
   "parenttype": null, 
   "property": "permlevel", 
   "property_type": "Int", 
   "value": "1"
  }, 
  {
   "_assign": null, 
   "_comments": null, 
   "_liked_by": null, 
   "_user_tags": null, 
   "creation": "2016-09-22 23:17:23.323081", 
   "default_value": null, 
   "doc_type": "Timesheet", 
   "docstatus": 0, 
   "doctype_or_field": "DocField", 
   "field_name": "total_billable_amount", 
   "idx": 0, 
   "modified": "2016-09-22 23:17:23.323081", 
   "modified_by": "blefebvre@aptitudetech.net", 
   "name": "Timesheet-total_billing_amount-permlevel", 
   "owner": "blefebvre@aptitudetech.net", 
   "parent": null, 
   "parentfield": null, 
   "parenttype": null, 
   "property": "permlevel", 
   "property_type": "Int", 
   "value": "1"
  }
 ], 
 "sync_on_migrate": 1
}